{"get":"fixtures\/events","parameters":{"fixture":"1223758"},"errors":[],"results":11,"paging":{"current":1,"total":1},"response":[{"time":{"elapsed":25,"extra":null},"team":{"id":489,"name":"AC Milan","logo":"https:\/\/media.api-sports.io\/football\/teams\/489.png"},"player":{"id":1566,"name":"Emerson Royal"},"assist":{"id":null,"name":null},"type":"Card","detail":"Yellow Card","comments":"Foul"},{"time":{"elapsed":32,"extra":null},"team":{"id":489,"name":"AC Milan","logo":"https:\/\/media.api-sports.io\/football\/teams\/489.png"},"player":{"id":22236,"name":"Rafael Le\u00e3o"},"assist":{"id":47300,"name":"T. Hern\u00e1ndez"},"type":"subst","detail":"Substitution 1","comments":null},{"time":{"elapsed":35,"extra":null},"team":{"id":504,"name":"Verona","logo":"https:\/\/media.api-sports.io\/football\/teams\/504.png"},"player":{"id":30921,"name":"Pawe\u0142 Dawidowicz"},"assist":{"id":null,"name":null},"type":"Card","detail":"Yellow Card","comments":"Foul"},{"time":{"elapsed":46,"extra":null},"team":{"id":504,"name":"Verona","logo":"https:\/\/media.api-sports.io\/football\/teams\/504.png"},"player":{"id":236955,"name":"A. Sarr"},"assist":{"id":343287,"name":"Dailon Livramento"},"type":"subst","detail":"Substitution 1","comments":null},{"time":{"elapsed":46,"extra":null},"team":{"id":504,"name":"Verona","logo":"https:\/\/media.api-sports.io\/football\/teams\/504.png"},"player":{"id":30921,"name":"P. Dawidowicz"},"assist":{"id":125715,"name":"F. Daniliuc"},"type":"subst","detail":"Substitution 2","comments":null},{"time":{"elapsed":56,"extra":null},"team":{"id":489,"name":"AC Milan","logo":"https:\/\/media.api-sports.io\/football\/teams\/489.png"},"player":{"id":36902,"name":"T. Reijnders"},"assist":{"id":22254,"name":"Y. Fofana"},"type":"Goal","detail":"Normal Goal","comments":null},{"time":{"elapsed":59,"extra":null},"team":{"id":504,"name":"Verona","logo":"https:\/\/media.api-sports.io\/football\/teams\/504.png"},"player":{"id":867,"name":"G. Kastanos"},"assist":{"id":418,"name":"S. Serdar"},"type":"subst","detail":"Substitution 3","comments":null},{"time":{"elapsed":70,"extra":null},"team":{"id":489,"name":"AC Milan","logo":"https:\/\/media.api-sports.io\/football\/teams\/489.png"},"player":{"id":1696,"name":"S. Chukwueze"},"assist":{"id":1627,"name":"D. Calabria"},"type":"subst","detail":"Substitution 2","comments":null},{"time":{"elapsed":73,"extra":null},"team":{"id":504,"name":"Verona","logo":"https:\/\/media.api-sports.io\/football\/teams\/504.png"},"player":{"id":2822,"name":"D. Lazovi\u0107"},"assist":{"id":59421,"name":"D. Mosquera"},"type":"subst","detail":"Substitution 4","comments":null},{"time":{"elapsed":80,"extra":null},"team":{"id":504,"name":"Verona","logo":"https:\/\/media.api-sports.io\/football\/teams\/504.png"},"player":{"id":333116,"name":"R. Belahyane"},"assist":{"id":162703,"name":"C. Tengstedt"},"type":"subst","detail":"Substitution 5","comments":null},{"time":{"elapsed":88,"extra":null},"team":{"id":489,"name":"AC Milan","logo":"https:\/\/media.api-sports.io\/football\/teams\/489.png"},"player":{"id":1566,"name":"Emerson Royal"},"assist":{"id":19209,"name":"F. Tomori"},"type":"subst","detail":"Substitution 3","comments":null}]}