{"get":"fixtures\/events","parameters":{"fixture":"1220976"},"errors":[],"results":14,"paging":{"current":1,"total":1},"response":[{"time":{"elapsed":16,"extra":null},"team":{"id":572,"name":"Dynamo Kyiv","logo":"https:\/\/media.api-sports.io\/football\/teams\/572.png"},"player":{"id":161670,"name":"V. Vanat"},"assist":{"id":2172,"name":"V. Buialskyi"},"type":"Goal","detail":"Normal Goal","comments":null},{"time":{"elapsed":64,"extra":null},"team":{"id":3615,"name":"Chornomorets","logo":"https:\/\/media.api-sports.io\/football\/teams\/3615.png"},"player":{"id":161572,"name":"B. Biloshevskyi"},"assist":{"id":1516,"name":"A. Habelok"},"type":"subst","detail":"Substitution 1","comments":null},{"time":{"elapsed":69,"extra":null},"team":{"id":572,"name":"Dynamo Kyiv","logo":"https:\/\/media.api-sports.io\/football\/teams\/572.png"},"player":{"id":2172,"name":"V. Buialskyi"},"assist":{"id":161670,"name":"V. Vanat"},"type":"Goal","detail":"Normal Goal","comments":null},{"time":{"elapsed":71,"extra":null},"team":{"id":3615,"name":"Chornomorets","logo":"https:\/\/media.api-sports.io\/football\/teams\/3615.png"},"player":{"id":334518,"name":"Moses Jarju"},"assist":{"id":null,"name":null},"type":"Card","detail":"Yellow Card","comments":null},{"time":{"elapsed":76,"extra":null},"team":{"id":3615,"name":"Chornomorets","logo":"https:\/\/media.api-sports.io\/football\/teams\/3615.png"},"player":{"id":336625,"name":"K. Siheiev"},"assist":{"id":150690,"name":"I. Shevtsov"},"type":"subst","detail":"Substitution 2","comments":null},{"time":{"elapsed":76,"extra":null},"team":{"id":3615,"name":"Chornomorets","logo":"https:\/\/media.api-sports.io\/football\/teams\/3615.png"},"player":{"id":334518,"name":"M. Jarju"},"assist":{"id":383853,"name":"Y. Skyba"},"type":"subst","detail":"Substitution 3","comments":null},{"time":{"elapsed":77,"extra":null},"team":{"id":572,"name":"Dynamo Kyiv","logo":"https:\/\/media.api-sports.io\/football\/teams\/572.png"},"player":{"id":161670,"name":"V. Vanat"},"assist":{"id":95105,"name":"E. Guerrero"},"type":"subst","detail":"Substitution 1","comments":null},{"time":{"elapsed":77,"extra":null},"team":{"id":572,"name":"Dynamo Kyiv","logo":"https:\/\/media.api-sports.io\/football\/teams\/572.png"},"player":{"id":55877,"name":"O. Karavaiev"},"assist":{"id":198391,"name":"N. Voloshyn"},"type":"subst","detail":"Substitution 2","comments":null},{"time":{"elapsed":84,"extra":null},"team":{"id":572,"name":"Dynamo Kyiv","logo":"https:\/\/media.api-sports.io\/football\/teams\/572.png"},"player":{"id":63452,"name":"V. Kabaiev"},"assist":{"id":63637,"name":"V. Rubchynskyi"},"type":"subst","detail":"Substitution 3","comments":null},{"time":{"elapsed":84,"extra":null},"team":{"id":572,"name":"Dynamo Kyiv","logo":"https:\/\/media.api-sports.io\/football\/teams\/572.png"},"player":{"id":2177,"name":"M. Shaparenko"},"assist":{"id":161570,"name":"M. Mykhailenko"},"type":"subst","detail":"Substitution 4","comments":null},{"time":{"elapsed":87,"extra":null},"team":{"id":572,"name":"Dynamo Kyiv","logo":"https:\/\/media.api-sports.io\/football\/teams\/572.png"},"player":{"id":63637,"name":"V. Rubchynskyi"},"assist":{"id":null,"name":null},"type":"Goal","detail":"Normal Goal","comments":null},{"time":{"elapsed":88,"extra":null},"team":{"id":3615,"name":"Chornomorets","logo":"https:\/\/media.api-sports.io\/football\/teams\/3615.png"},"player":{"id":402723,"name":"Caio Gomes"},"assist":{"id":478418,"name":"O. Pshenychniuk"},"type":"subst","detail":"Substitution 4","comments":null},{"time":{"elapsed":90,"extra":null},"team":{"id":572,"name":"Dynamo Kyiv","logo":"https:\/\/media.api-sports.io\/football\/teams\/572.png"},"player":{"id":2172,"name":"V. Buialskyi"},"assist":{"id":328765,"name":"R. Salenko"},"type":"subst","detail":"Substitution 5","comments":null},{"time":{"elapsed":90,"extra":2},"team":{"id":3615,"name":"Chornomorets","logo":"https:\/\/media.api-sports.io\/football\/teams\/3615.png"},"player":{"id":383853,"name":"Y. Skyba"},"assist":{"id":28340,"name":"I. Petriak"},"type":"Goal","detail":"Normal Goal","comments":null}]}