{"get":"fixtures\/events","parameters":{"fixture":"1035421"},"errors":[],"results":20,"paging":{"current":1,"total":1},"response":[{"time":{"elapsed":8,"extra":null},"team":{"id":48,"name":"West Ham","logo":"https:\/\/media.api-sports.io\/football\/teams\/48.png"},"player":{"id":15911,"name":"Mohammed Kudus"},"assist":{"id":null,"name":null},"type":"Card","detail":"Yellow Card","comments":"Foul"},{"time":{"elapsed":9,"extra":null},"team":{"id":65,"name":"Nottingham Forest","logo":"https:\/\/media.api-sports.io\/football\/teams\/65.png"},"player":{"id":18746,"name":"Morgan Gibbs-White"},"assist":{"id":null,"name":null},"type":"Card","detail":"Yellow Card","comments":"Foul"},{"time":{"elapsed":36,"extra":null},"team":{"id":48,"name":"West Ham","logo":"https:\/\/media.api-sports.io\/football\/teams\/48.png"},"player":{"id":18819,"name":"Michail Antonio"},"assist":{"id":null,"name":null},"type":"Card","detail":"Yellow Card","comments":"Argument"},{"time":{"elapsed":45,"extra":6},"team":{"id":65,"name":"Nottingham Forest","logo":"https:\/\/media.api-sports.io\/football\/teams\/65.png"},"player":{"id":8598,"name":"Taiwo Awoniyi"},"assist":{"id":null,"name":null},"type":"Card","detail":"Yellow Card","comments":null},{"time":{"elapsed":45,"extra":5},"team":{"id":65,"name":"Nottingham Forest","logo":"https:\/\/media.api-sports.io\/football\/teams\/65.png"},"player":{"id":8598,"name":"T. Awoniyi"},"assist":{"id":6056,"name":"N. Dom\u00ednguez"},"type":"Goal","detail":"Normal Goal","comments":null},{"time":{"elapsed":57,"extra":null},"team":{"id":48,"name":"West Ham","logo":"https:\/\/media.api-sports.io\/football\/teams\/48.png"},"player":{"id":2726,"name":"Kurt Zouma"},"assist":{"id":null,"name":null},"type":"Card","detail":"Yellow Card","comments":"Persistent fouling"},{"time":{"elapsed":60,"extra":null},"team":{"id":65,"name":"Nottingham Forest","logo":"https:\/\/media.api-sports.io\/football\/teams\/65.png"},"player":{"id":138780,"name":"Neco Williams"},"assist":{"id":null,"name":null},"type":"Card","detail":"Yellow Card","comments":"Foul"},{"time":{"elapsed":67,"extra":null},"team":{"id":65,"name":"Nottingham Forest","logo":"https:\/\/media.api-sports.io\/football\/teams\/65.png"},"player":{"id":8598,"name":"T. Awoniyi"},"assist":{"id":305,"name":"D. Origi"},"type":"subst","detail":"Substitution 1","comments":null},{"time":{"elapsed":68,"extra":null},"team":{"id":48,"name":"West Ham","logo":"https:\/\/media.api-sports.io\/football\/teams\/48.png"},"player":{"id":19130,"name":"Kalvin Phillips"},"assist":{"id":null,"name":null},"type":"Card","detail":"Yellow Card","comments":"Argument"},{"time":{"elapsed":68,"extra":null},"team":{"id":48,"name":"West Ham","logo":"https:\/\/media.api-sports.io\/football\/teams\/48.png"},"player":{"id":1231,"name":"Vladim\u00edr Coufal"},"assist":{"id":null,"name":null},"type":"Card","detail":"Yellow Card","comments":"Foul"},{"time":{"elapsed":68,"extra":null},"team":{"id":65,"name":"Nottingham Forest","logo":"https:\/\/media.api-sports.io\/football\/teams\/65.png"},"player":{"id":6056,"name":"Nicol\u00e1s Dom\u00ednguez"},"assist":{"id":null,"name":null},"type":"Card","detail":"Yellow Card","comments":"Argument"},{"time":{"elapsed":71,"extra":null},"team":{"id":48,"name":"West Ham","logo":"https:\/\/media.api-sports.io\/football\/teams\/48.png"},"player":{"id":19130,"name":"Kalvin Phillips"},"assist":{"id":null,"name":null},"type":"Card","detail":"Red Card","comments":"Foul"},{"time":{"elapsed":71,"extra":null},"team":{"id":48,"name":"West Ham","logo":"https:\/\/media.api-sports.io\/football\/teams\/48.png"},"player":{"id":19130,"name":"Kalvin Phillips"},"assist":{"id":null,"name":null},"type":"Card","detail":"Yellow Card","comments":"Foul"},{"time":{"elapsed":75,"extra":null},"team":{"id":48,"name":"West Ham","logo":"https:\/\/media.api-sports.io\/football\/teams\/48.png"},"player":{"id":18819,"name":"M. Antonio"},"assist":{"id":665,"name":"M. Cornet"},"type":"subst","detail":"Substitution 1","comments":null},{"time":{"elapsed":76,"extra":null},"team":{"id":48,"name":"West Ham","logo":"https:\/\/media.api-sports.io\/football\/teams\/48.png"},"player":{"id":1231,"name":"V. Coufal"},"assist":{"id":18823,"name":"B. Johnson"},"type":"subst","detail":"Substitution 2","comments":null},{"time":{"elapsed":83,"extra":null},"team":{"id":48,"name":"West Ham","logo":"https:\/\/media.api-sports.io\/football\/teams\/48.png"},"player":{"id":2284,"name":"Emerson"},"assist":{"id":1243,"name":"T. Sou\u010dek"},"type":"subst","detail":"Substitution 3","comments":null},{"time":{"elapsed":86,"extra":null},"team":{"id":65,"name":"Nottingham Forest","logo":"https:\/\/media.api-sports.io\/football\/teams\/65.png"},"player":{"id":6056,"name":"N. Dom\u00ednguez"},"assist":{"id":19305,"name":"R. Yates"},"type":"subst","detail":"Substitution 2","comments":null},{"time":{"elapsed":90,"extra":3},"team":{"id":65,"name":"Nottingham Forest","logo":"https:\/\/media.api-sports.io\/football\/teams\/65.png"},"player":{"id":18746,"name":"M. Gibbs-White"},"assist":{"id":147835,"name":"A. Omobamidele"},"type":"subst","detail":"Substitution 3","comments":null},{"time":{"elapsed":90,"extra":3},"team":{"id":48,"name":"West Ham","logo":"https:\/\/media.api-sports.io\/football\/teams\/48.png"},"player":{"id":2726,"name":"K. Zouma"},"assist":{"id":18955,"name":"D. Ings"},"type":"subst","detail":"Substitution 4","comments":null},{"time":{"elapsed":90,"extra":4},"team":{"id":65,"name":"Nottingham Forest","logo":"https:\/\/media.api-sports.io\/football\/teams\/65.png"},"player":{"id":2298,"name":"C. Hudson-Odoi"},"assist":{"id":153430,"name":"A. Elanga"},"type":"Goal","detail":"Normal Goal","comments":null}]}