{"get":"fixtures\/events","parameters":{"fixture":"1062676"},"errors":[],"results":17,"paging":{"current":1,"total":1},"response":[{"time":{"elapsed":5,"extra":null},"team":{"id":17161,"name":"LNZ Cherkasy","logo":"https:\/\/media.api-sports.io\/football\/teams\/17161.png"},"player":{"id":50093,"name":"Serhiy Rybalka"},"assist":{"id":null,"name":null},"type":"Card","detail":"Yellow Card","comments":null},{"time":{"elapsed":8,"extra":null},"team":{"id":6496,"name":"Polessya","logo":"https:\/\/media.api-sports.io\/football\/teams\/6496.png"},"player":{"id":274614,"name":"Denys Ndukve"},"assist":{"id":null,"name":null},"type":"Card","detail":"Yellow Card","comments":null},{"time":{"elapsed":27,"extra":null},"team":{"id":17161,"name":"LNZ Cherkasy","logo":"https:\/\/media.api-sports.io\/football\/teams\/17161.png"},"player":{"id":162486,"name":"Nazarii Muravskyi"},"assist":{"id":null,"name":null},"type":"Card","detail":"Yellow Card","comments":null},{"time":{"elapsed":42,"extra":null},"team":{"id":6496,"name":"Polessya","logo":"https:\/\/media.api-sports.io\/football\/teams\/6496.png"},"player":{"id":2176,"name":"Mykyta Kravchenko"},"assist":{"id":null,"name":null},"type":"Card","detail":"Yellow Card","comments":null},{"time":{"elapsed":57,"extra":null},"team":{"id":17161,"name":"LNZ Cherkasy","logo":"https:\/\/media.api-sports.io\/football\/teams\/17161.png"},"player":{"id":134973,"name":"Arad Bar"},"assist":{"id":null,"name":null},"type":"Card","detail":"Yellow Card","comments":null},{"time":{"elapsed":66,"extra":null},"team":{"id":17161,"name":"LNZ Cherkasy","logo":"https:\/\/media.api-sports.io\/football\/teams\/17161.png"},"player":{"id":53716,"name":"O. Thill"},"assist":{"id":55354,"name":"D. Oliinyk"},"type":"subst","detail":"Substitution 1","comments":null},{"time":{"elapsed":66,"extra":null},"team":{"id":17161,"name":"LNZ Cherkasy","logo":"https:\/\/media.api-sports.io\/football\/teams\/17161.png"},"player":{"id":26924,"name":"V. Naumets"},"assist":{"id":28595,"name":"S. Shestakov"},"type":"subst","detail":"Substitution 2","comments":null},{"time":{"elapsed":66,"extra":null},"team":{"id":17161,"name":"LNZ Cherkasy","logo":"https:\/\/media.api-sports.io\/football\/teams\/17161.png"},"player":{"id":50093,"name":"S. Rybalka"},"assist":{"id":126803,"name":"V. Boiko"},"type":"subst","detail":"Substitution 3","comments":null},{"time":{"elapsed":69,"extra":null},"team":{"id":6496,"name":"Polessya","logo":"https:\/\/media.api-sports.io\/football\/teams\/6496.png"},"player":{"id":48535,"name":"Y. Fortun\u00e9"},"assist":{"id":63635,"name":"O. Nazarenko"},"type":"subst","detail":"Substitution 1","comments":null},{"time":{"elapsed":69,"extra":null},"team":{"id":6496,"name":"Polessya","logo":"https:\/\/media.api-sports.io\/football\/teams\/6496.png"},"player":{"id":277248,"name":"B. Krushynskyi"},"assist":{"id":63391,"name":"V. Hrytsuk"},"type":"subst","detail":"Substitution 2","comments":null},{"time":{"elapsed":77,"extra":null},"team":{"id":6496,"name":"Polessya","logo":"https:\/\/media.api-sports.io\/football\/teams\/6496.png"},"player":{"id":180925,"name":"Talles Costa"},"assist":{"id":313949,"name":"E. Mustafaev"},"type":"subst","detail":"Substitution 3","comments":null},{"time":{"elapsed":77,"extra":null},"team":{"id":17161,"name":"LNZ Cherkasy","logo":"https:\/\/media.api-sports.io\/football\/teams\/17161.png"},"player":{"id":409843,"name":"G. Bessala"},"assist":{"id":7818,"name":"O. Khoblenko"},"type":"subst","detail":"Substitution 4","comments":null},{"time":{"elapsed":89,"extra":null},"team":{"id":17161,"name":"LNZ Cherkasy","logo":"https:\/\/media.api-sports.io\/football\/teams\/17161.png"},"player":{"id":63519,"name":"Hennadii Pasich"},"assist":{"id":null,"name":null},"type":"Card","detail":"Yellow Card","comments":null},{"time":{"elapsed":89,"extra":null},"team":{"id":17161,"name":"LNZ Cherkasy","logo":"https:\/\/media.api-sports.io\/football\/teams\/17161.png"},"player":{"id":134973,"name":"A. Bar"},"assist":{"id":122265,"name":"O. Tarasenko"},"type":"subst","detail":"Substitution 5","comments":null},{"time":{"elapsed":90,"extra":4},"team":{"id":17161,"name":"LNZ Cherkasy","logo":"https:\/\/media.api-sports.io\/football\/teams\/17161.png"},"player":{"id":55354,"name":"Denys Oliynyk"},"assist":{"id":null,"name":null},"type":"Card","detail":"Yellow Card","comments":null},{"time":{"elapsed":90,"extra":5},"team":{"id":17161,"name":"LNZ Cherkasy","logo":"https:\/\/media.api-sports.io\/football\/teams\/17161.png"},"player":{"id":122265,"name":"Oleh Tarasenko"},"assist":{"id":null,"name":null},"type":"Card","detail":"Yellow Card","comments":null},{"time":{"elapsed":90,"extra":2},"team":{"id":17161,"name":"LNZ Cherkasy","logo":"https:\/\/media.api-sports.io\/football\/teams\/17161.png"},"player":{"id":55354,"name":"D. Oliinyk"},"assist":{"id":null,"name":null},"type":"Goal","detail":"Normal Goal","comments":null}]}