{"get":"fixtures\/events","parameters":{"fixture":"1223655"},"errors":[],"results":17,"paging":{"current":1,"total":1},"response":[{"time":{"elapsed":24,"extra":null},"team":{"id":499,"name":"Atalanta","logo":"https:\/\/media.api-sports.io\/football\/teams\/499.png"},"player":{"id":6420,"name":"M. Retegui"},"assist":{"id":18767,"name":"A. Lookman"},"type":"Goal","detail":"Normal Goal","comments":null},{"time":{"elapsed":46,"extra":null},"team":{"id":495,"name":"Genoa","logo":"https:\/\/media.api-sports.io\/football\/teams\/495.png"},"player":{"id":30736,"name":"M. Bani"},"assist":{"id":31521,"name":"A. Vogliacco"},"type":"subst","detail":"Substitution 1","comments":null},{"time":{"elapsed":50,"extra":null},"team":{"id":499,"name":"Atalanta","logo":"https:\/\/media.api-sports.io\/football\/teams\/499.png"},"player":{"id":6420,"name":"M. Retegui"},"assist":{"id":null,"name":null},"type":"Goal","detail":"Normal Goal","comments":null},{"time":{"elapsed":60,"extra":null},"team":{"id":499,"name":"Atalanta","logo":"https:\/\/media.api-sports.io\/football\/teams\/499.png"},"player":{"id":10097,"name":"\u00c9derson"},"assist":{"id":6420,"name":"M. Retegui"},"type":"Goal","detail":"Normal Goal","comments":null},{"time":{"elapsed":67,"extra":null},"team":{"id":495,"name":"Genoa","logo":"https:\/\/media.api-sports.io\/football\/teams\/495.png"},"player":{"id":31094,"name":"A. Pinamonti"},"assist":{"id":451504,"name":"J. Ekhator"},"type":"subst","detail":"Substitution 2","comments":null},{"time":{"elapsed":67,"extra":null},"team":{"id":495,"name":"Genoa","logo":"https:\/\/media.api-sports.io\/football\/teams\/495.png"},"player":{"id":181808,"name":"F. Miretti"},"assist":{"id":31493,"name":"F. Melegoni"},"type":"subst","detail":"Substitution 3","comments":null},{"time":{"elapsed":68,"extra":null},"team":{"id":499,"name":"Atalanta","logo":"https:\/\/media.api-sports.io\/football\/teams\/499.png"},"player":{"id":147859,"name":"C. De Ketelaere"},"assist":{"id":178749,"name":"L. Samard\u017ei\u0107"},"type":"subst","detail":"Substitution 1","comments":null},{"time":{"elapsed":68,"extra":null},"team":{"id":499,"name":"Atalanta","logo":"https:\/\/media.api-sports.io\/football\/teams\/499.png"},"player":{"id":18767,"name":"A. Lookman"},"assist":{"id":786,"name":"N. Zaniolo"},"type":"subst","detail":"Substitution 2","comments":null},{"time":{"elapsed":73,"extra":null},"team":{"id":499,"name":"Atalanta","logo":"https:\/\/media.api-sports.io\/football\/teams\/499.png"},"player":{"id":178749,"name":"Lazar Samard\u017ei\u0107"},"assist":{"id":null,"name":null},"type":"Var","detail":"Penalty confirmed","comments":null},{"time":{"elapsed":74,"extra":null},"team":{"id":499,"name":"Atalanta","logo":"https:\/\/media.api-sports.io\/football\/teams\/499.png"},"player":{"id":6420,"name":"M. Retegui"},"assist":{"id":null,"name":null},"type":"Goal","detail":"Penalty","comments":null},{"time":{"elapsed":78,"extra":null},"team":{"id":499,"name":"Atalanta","logo":"https:\/\/media.api-sports.io\/football\/teams\/499.png"},"player":{"id":10097,"name":"\u00c9derson"},"assist":{"id":353609,"name":"I. Sulemana"},"type":"subst","detail":"Substitution 3","comments":null},{"time":{"elapsed":78,"extra":null},"team":{"id":499,"name":"Atalanta","logo":"https:\/\/media.api-sports.io\/football\/teams\/499.png"},"player":{"id":91422,"name":"R. Bellanova"},"assist":{"id":383018,"name":"M. Palestra"},"type":"subst","detail":"Substitution 4","comments":null},{"time":{"elapsed":80,"extra":null},"team":{"id":499,"name":"Atalanta","logo":"https:\/\/media.api-sports.io\/football\/teams\/499.png"},"player":{"id":30432,"name":"M. de Roon"},"assist":{"id":null,"name":null},"type":"Goal","detail":"Normal Goal","comments":null},{"time":{"elapsed":81,"extra":null},"team":{"id":495,"name":"Genoa","logo":"https:\/\/media.api-sports.io\/football\/teams\/495.png"},"player":{"id":25914,"name":"Aar\u00f3n Mart\u00edn"},"assist":{"id":284570,"name":"B. Norton-Cuffy"},"type":"subst","detail":"Substitution 4","comments":null},{"time":{"elapsed":82,"extra":null},"team":{"id":499,"name":"Atalanta","logo":"https:\/\/media.api-sports.io\/football\/teams\/499.png"},"player":{"id":6420,"name":"M. Retegui"},"assist":{"id":290807,"name":"V. Vlahovi\u0107"},"type":"subst","detail":"Substitution 5","comments":null},{"time":{"elapsed":83,"extra":null},"team":{"id":495,"name":"Genoa","logo":"https:\/\/media.api-sports.io\/football\/teams\/495.png"},"player":{"id":451504,"name":"J. Ekhator"},"assist":{"id":31493,"name":"F. Melegoni"},"type":"Goal","detail":"Normal Goal","comments":null},{"time":{"elapsed":86,"extra":null},"team":{"id":495,"name":"Genoa","logo":"https:\/\/media.api-sports.io\/football\/teams\/495.png"},"player":{"id":281408,"name":"V\u00edtinha"},"assist":{"id":310109,"name":"D. Ankeye"},"type":"subst","detail":"Substitution 5","comments":null}]}